<?xml version='1.0' encoding='UTF-8'?>
<fops:StandardBillingDocument xmlns:fops="http://www.fieldops-demo.io/xml/ns" type="APINVOICE"><fops:SummaryInvoice id="65065437">
<fops:DocumentHeader>
<fops:DocumentNumber>1856993769</fops:DocumentNumber>
<fops:Party PartyRole="Vendor">
<fops:Entity>
<fops:EntityCode EntityCodeType="VendorID">VEND921508</fops:EntityCode>
<fops:EntityName>Jones-Hughes</fops:EntityName>
</fops:Entity>
<fops:Location>
<fops:LocationCode LocationCodeType="AssignedByClient">GZ-0448-DRWA</fops:LocationCode>
<fops:LocationName>Fire Block</fops:LocationName>
<fops:Address AddressType="Mailing">
<fops:AddressLine>8645 Brent Pike Suite 212</fops:AddressLine>
<fops:City>East Donna</fops:City>
<fops:StateProvince>Texas</fops:StateProvince>
<fops:StateProvinceCode>TX</fops:StateProvinceCode>
<fops:Country>United States of America</fops:Country>
<fops:CountryCode>US</fops:CountryCode>
<fops:PostalZipCode>67277</fops:PostalZipCode>
<fops:EmailAddress>sydney42@arnold.net</fops:EmailAddress>
</fops:Address>
</fops:Location>
</fops:Party>
<fops:Party PartyRole="Client">
<fops:Entity>
<fops:EntityCode EntityCodeType="GlobalID">052689837</fops:EntityCode>
<fops:EntityName>Perkins Wilkins and Smith</fops:EntityName>
</fops:Entity>
<fops:Location>
<fops:LocationCode LocationCodeType="AssignedByClient">YB-6290-TCWD</fops:LocationCode>
<fops:LocationName>Society Basin</fops:LocationName>
<fops:Address AddressType="Mailing">
<fops:AddressLine>69329 Cole Parkways</fops:AddressLine>
<fops:City>Jeffreyton</fops:City>
<fops:StateProvince>Oklahoma</fops:StateProvince>
<fops:StateProvinceCode>OK</fops:StateProvinceCode>
<fops:Country>United States of America</fops:Country>
<fops:CountryCode>US</fops:CountryCode>
<fops:PostalZipCode>34489</fops:PostalZipCode>
</fops:Address>
</fops:Location>
</fops:Party>
<fops:DocumentDate>2015-01-22</fops:DocumentDate>
<fops:DocumentType>Original Invoice</fops:DocumentType>
<fops:SubmissionMethod>Supplier_Image_Direct</fops:SubmissionMethod>
<fops:Total>1550</fops:Total>
<fops:VendorTotal>1550</fops:VendorTotal>
<fops:LineCount>1</fops:LineCount>
<fops:Notes>Field maintenance and inspection services</fops:Notes>
<fops:CurrencyCode>USD</fops:CurrencyCode>
<fops:Action>
<fops:Contact Role="DocumentActionPerformer">
<fops:FirstName>George</fops:FirstName>
<fops:LastName>Russell</fops:LastName>
<fops:EmailAddress>robertmorrison@griffin-soto.com</fops:EmailAddress>
<fops:Location>
<fops:LocationCode LocationCodeType="AssignedByClient">QU-2332-RYWO</fops:LocationCode>
<fops:LocationName>Pick Basin</fops:LocationName>
</fops:Location>
<fops:Department>
<fops:DepartmentName>Accounts Payable</fops:DepartmentName>
</fops:Department>
</fops:Contact>
<fops:ActionType>Approve</fops:ActionType>
<fops:Status>Approved</fops:Status>
<fops:Notes>Environmental monitoring and compliance</fops:Notes>
<fops:TransactionDateTime>2014-07-23T08:12:41</fops:TransactionDateTime>
<fops:TransactionIdentifier>51327</fops:TransactionIdentifier>
<fops:ActionSource role="DocumentActionPerformer">
<fops:FirstName>Tonya</fops:FirstName>
<fops:LastName>Browning</fops:LastName>
<fops:EmailAddress>rogersamanda@reed.com</fops:EmailAddress>
<fops:Location>
<fops:LocationCode siteCodeIndicator="AssignedByClient">TF-7665-TZWL</fops:LocationCode>
<fops:LocationName>Military Well</fops:LocationName>
</fops:Location>
<fops:Department>
<fops:DepartmentName>Accounts Payable</fops:DepartmentName>
</fops:Department>
</fops:ActionSource>
</fops:Action>
<fops:DiscountTotal>0</fops:DiscountTotal>
<fops:CurrentOwner>
<fops:Department>
<fops:DepartmentName>Accounts Payable</fops:DepartmentName>
</fops:Department>
</fops:CurrentOwner>
</fops:DocumentHeader>
<fops:DocumentLines>
<fops:Allocation>
<fops:AllocationRate>1</fops:AllocationRate>
<fops:Total>1550</fops:Total>
</fops:Allocation>
<fops:LineEntry>
<fops:LineNumber>1</fops:LineNumber>
<fops:Quantity>1</fops:Quantity>
<fops:UnitPrice>1550</fops:UnitPrice>
<fops:Notes>Chemical treatment program — Q3 operations</fops:Notes>
<fops:Discount>
<fops:Total>0</fops:Total>
<fops:AllocationRate>0</fops:AllocationRate>
</fops:Discount>
<fops:Category CategorizationScheme="ocpChargeType">
<fops:CategoryCode>Other</fops:CategoryCode>
</fops:Category>
<fops:Allocation>
<fops:AllocationRate>1</fops:AllocationRate>
<fops:Total>1550</fops:Total>
</fops:Allocation>
<fops:ChargeClass>Non-Itemized</fops:ChargeClass>
</fops:LineEntry>
</fops:DocumentLines>
</fops:SummaryInvoice>
<fops:Attachments numOfAttachments="2">
<fops:Attachment type="pdfInvoice" id="0genPdf65065437">
<fops:LocationPath>/docp/supply-chain/v1/invoices/65065437/snapshot</fops:LocationPath>
<fops:ContentType>application/pdf</fops:ContentType>
</fops:Attachment>
</fops:Attachments>
</fops:StandardBillingDocument>
