<?xml version='1.0' encoding='UTF-8'?>
<fops:StandardBillingDocument xmlns:fops="http://www.fieldops-demo.io/xml/ns" type="APINVOICE"><fops:DetailedInvoice id="63732295">
<fops:DocumentHeader>
<fops:DocumentNumber>2672768304</fops:DocumentNumber>
<fops:Party PartyRole="Vendor">
<fops:Entity>
<fops:EntityCode EntityCodeType="VendorID">VEND439623</fops:EntityCode>
<fops:EntityName>Smith-Kelly</fops:EntityName>
</fops:Entity>
<fops:Location>
<fops:LocationCode LocationCodeType="AssignedByClient">IN-7720-JTWN</fops:LocationCode>
<fops:LocationName>Care Field</fops:LocationName>
<fops:Address AddressType="Mailing">
<fops:AddressLine>27571 Acosta Via Apt. 457</fops:AddressLine>
<fops:City>Bennettside</fops:City>
<fops:StateProvince>Texas</fops:StateProvince>
<fops:StateProvinceCode>TX</fops:StateProvinceCode>
<fops:Country>United States of America</fops:Country>
<fops:CountryCode>US</fops:CountryCode>
<fops:PostalZipCode>64629</fops:PostalZipCode>
<fops:PhoneNumber PhoneNumberType="Primary">0986069422</fops:PhoneNumber>
<fops:EmailAddress>christopherlambert@johnson.com</fops:EmailAddress>
</fops:Address>
</fops:Location>
</fops:Party>
<fops:Party PartyRole="Client">
<fops:Entity>
<fops:EntityCode EntityCodeType="GlobalID">536801333</fops:EntityCode>
<fops:EntityName>Olson Miller and Griffith</fops:EntityName>
</fops:Entity>
<fops:Location>
<fops:LocationCode LocationCodeType="AssignedByClient">JW-6113-WGWX</fops:LocationCode>
<fops:LocationName>Agent Well</fops:LocationName>
<fops:Address AddressType="Mailing">
<fops:AddressLine>699 Sylvia Lock Apt. 654</fops:AddressLine>
<fops:City>Loweside</fops:City>
<fops:StateProvince>Oklahoma</fops:StateProvince>
<fops:StateProvinceCode>OK</fops:StateProvinceCode>
<fops:Country>United States of America</fops:Country>
<fops:CountryCode>US</fops:CountryCode>
<fops:PostalZipCode>72020</fops:PostalZipCode>
</fops:Address>
</fops:Location>
</fops:Party>
<fops:DocumentDate>2013-12-18</fops:DocumentDate>
<fops:DocumentType>Original Invoice</fops:DocumentType>
<fops:SubmissionMethod>Supplier_Regular_Direct</fops:SubmissionMethod>
<fops:Total>2480</fops:Total>
<fops:VendorTotal>2480</fops:VendorTotal>
<fops:LineCount>2</fops:LineCount>
<fops:Notes>Environmental monitoring and compliance</fops:Notes>
<fops:CurrencyCode>USD</fops:CurrencyCode>
<fops:Action>
<fops:Contact Role="DocumentActionPerformer">
<fops:FirstName>Nathan</fops:FirstName>
<fops:LastName>Ellis</fops:LastName>
<fops:EmailAddress>timothy91@obrien.com</fops:EmailAddress>
<fops:Location>
<fops:LocationCode LocationCodeType="AssignedByClient">RA-4724-ULWL</fops:LocationCode>
<fops:LocationName>Until Pad</fops:LocationName>
</fops:Location>
<fops:Department>
<fops:DepartmentName>Accounts Payable</fops:DepartmentName>
</fops:Department>
</fops:Contact>
<fops:ActionType>Approve</fops:ActionType>
<fops:Status>Approved</fops:Status>
<fops:Notes>Consulting services for production optimization</fops:Notes>
<fops:TransactionDateTime>2014-07-24T10:40:50</fops:TransactionDateTime>
<fops:TransactionIdentifier>51327</fops:TransactionIdentifier>
<fops:ActionSource role="DocumentActionPerformer">
<fops:FirstName>Jacob</fops:FirstName>
<fops:LastName>Bradley</fops:LastName>
<fops:EmailAddress>megan52@perkins.com</fops:EmailAddress>
<fops:Location>
<fops:LocationCode siteCodeIndicator="AssignedByClient">XR-0646-NVWM</fops:LocationCode>
<fops:LocationName>Each Basin</fops:LocationName>
</fops:Location>
<fops:Department>
<fops:DepartmentName>Accounts Payable</fops:DepartmentName>
</fops:Department>
</fops:ActionSource>
</fops:Action>
<fops:DiscountTotal>0</fops:DiscountTotal>
<fops:CurrentOwner>
<fops:Department>
<fops:DepartmentName>Accounts Payable</fops:DepartmentName>
</fops:Department>
</fops:CurrentOwner>
</fops:DocumentHeader>
<fops:DocumentLines>
<fops:LineEntry>
<fops:LineNumber>1</fops:LineNumber>
<fops:ServiceItem>
<fops:ServiceCode codeIndicator="AssignedByVendor">Tester 0/10,000 PSI</fops:ServiceCode>
<fops:ProductDescription>Wellhead Service</fops:ProductDescription>
</fops:ServiceItem>
<fops:Quantity>1</fops:Quantity>
<fops:Units>1</fops:Units>
<fops:UnitPrice>1500</fops:UnitPrice>
<fops:Notes>Mechanical services — compressor overhaul</fops:Notes>
<fops:PeriodStartDate>2013-12-17</fops:PeriodStartDate>
<fops:PeriodDate>2013-12-18</fops:PeriodDate>
<fops:Discount>
<fops:Total>0</fops:Total>
<fops:AllocationRate>0</fops:AllocationRate>
</fops:Discount>
<fops:LineSubTotal>1500</fops:LineSubTotal>
<fops:LinePretaxTotal>1500</fops:LinePretaxTotal>
<fops:Total>1500</fops:Total>
<fops:Category CategorizationScheme="ocpChargeType">
<fops:CategoryCode>Service and Equipment</fops:CategoryCode>
</fops:Category>
<fops:Allocation>
<fops:AllocationRate>1</fops:AllocationRate>
<fops:Total>1500</fops:Total>
</fops:Allocation>
<fops:ChargeClass>Itemized</fops:ChargeClass>
</fops:LineEntry>
<fops:LineEntry>
<fops:LineNumber>2</fops:LineNumber>
<fops:ServiceItem>
<fops:ServiceCode codeIndicator="AssignedByVendor">Tester over 8 hrs</fops:ServiceCode>
<fops:ProductDescription>Frac Tank</fops:ProductDescription>
</fops:ServiceItem>
<fops:Quantity>7</fops:Quantity>
<fops:Units>1</fops:Units>
<fops:UnitPrice>140</fops:UnitPrice>
<fops:Notes>Hot-shot transportation and logistics</fops:Notes>
<fops:PeriodStartDate>2013-12-17</fops:PeriodStartDate>
<fops:PeriodDate>2013-12-18</fops:PeriodDate>
<fops:Discount>
<fops:Total>0</fops:Total>
<fops:AllocationRate>0</fops:AllocationRate>
</fops:Discount>
<fops:LineSubTotal>980</fops:LineSubTotal>
<fops:LinePretaxTotal>980</fops:LinePretaxTotal>
<fops:Total>980</fops:Total>
<fops:Category CategorizationScheme="ocpChargeType">
<fops:CategoryCode>Service and Equipment</fops:CategoryCode>
</fops:Category>
<fops:Allocation>
<fops:AllocationRate>1</fops:AllocationRate>
<fops:Total>980</fops:Total>
</fops:Allocation>
<fops:ChargeClass>Itemized</fops:ChargeClass>
</fops:LineEntry>
</fops:DocumentLines>
</fops:DetailedInvoice>
<fops:Attachments numOfAttachments="2">
<fops:Attachment type="pdfInvoice" id="0genPdf63732295">
<fops:LocationPath>/docp/supply-chain/v1/invoices/63732295/snapshot</fops:LocationPath>
<fops:ContentType>application/pdf</fops:ContentType>
</fops:Attachment>
</fops:Attachments>
</fops:StandardBillingDocument>
