<?xml version='1.0' encoding='UTF-8'?>
<fops:StandardBillingDocument xmlns:fops="http://www.fieldops-demo.io/xml/ns" type="APINVOICE"><fops:SummaryInvoice id="64899656">
<fops:DocumentHeader>
<fops:DocumentNumber>3001764855</fops:DocumentNumber>
<fops:Party PartyRole="Vendor">
<fops:Entity>
<fops:EntityCode EntityCodeType="VendorID">VEND606251</fops:EntityCode>
<fops:EntityName>Graham-Diaz</fops:EntityName>
</fops:Entity>
<fops:Location>
<fops:LocationCode LocationCodeType="AssignedByClient">IU-3068-OSWG</fops:LocationCode>
<fops:LocationName>Ground Pad</fops:LocationName>
<fops:Address AddressType="Mailing">
<fops:AddressLine>130 Brittany Orchard</fops:AddressLine>
<fops:City>Vargasfurt</fops:City>
<fops:StateProvince>Texas</fops:StateProvince>
<fops:StateProvinceCode>TX</fops:StateProvinceCode>
<fops:Country>United States of America</fops:Country>
<fops:CountryCode>US</fops:CountryCode>
<fops:PostalZipCode>58312</fops:PostalZipCode>
<fops:PhoneNumber PhoneNumberType="Primary">8960573400</fops:PhoneNumber>
<fops:EmailAddress>mooreeric@bryant.info</fops:EmailAddress>
</fops:Address>
</fops:Location>
</fops:Party>
<fops:Party PartyRole="Client">
<fops:Entity>
<fops:EntityCode EntityCodeType="GlobalID">923903246</fops:EntityCode>
<fops:EntityName>Jimenez Garcia and Chandler</fops:EntityName>
</fops:Entity>
<fops:Location>
<fops:LocationCode LocationCodeType="AssignedByClient">VJ-3739-OSWR</fops:LocationCode>
<fops:LocationName>Read Lease</fops:LocationName>
<fops:Address AddressType="Mailing">
<fops:AddressLine>6520 Hannah Port</fops:AddressLine>
<fops:City>Omarstad</fops:City>
<fops:StateProvince>Oklahoma</fops:StateProvince>
<fops:StateProvinceCode>OK</fops:StateProvinceCode>
<fops:Country>United States of America</fops:Country>
<fops:CountryCode>US</fops:CountryCode>
<fops:PostalZipCode>95093</fops:PostalZipCode>
</fops:Address>
</fops:Location>
</fops:Party>
<fops:DocumentDate>2014-04-20</fops:DocumentDate>
<fops:DocumentType>Original Invoice</fops:DocumentType>
<fops:SubmissionMethod>Supplier_Image_Direct</fops:SubmissionMethod>
<fops:Total>466</fops:Total>
<fops:VendorTotal>466</fops:VendorTotal>
<fops:LineCount>1</fops:LineCount>
<fops:Notes>Electrical installation and commissioning</fops:Notes>
<fops:CurrencyCode>USD</fops:CurrencyCode>
<fops:Action>
<fops:Contact Role="DocumentActionPerformer">
<fops:FirstName>Joanna</fops:FirstName>
<fops:LastName>Williams</fops:LastName>
<fops:EmailAddress>manuel49@jones-gallagher.com</fops:EmailAddress>
<fops:Location>
<fops:LocationCode LocationCodeType="AssignedByClient">OG-6582-ZKWX</fops:LocationCode>
<fops:LocationName>Treatment Block</fops:LocationName>
</fops:Location>
<fops:Department>
<fops:DepartmentName>Accounts Payable</fops:DepartmentName>
</fops:Department>
</fops:Contact>
<fops:ActionType>Approve</fops:ActionType>
<fops:Status>Approved</fops:Status>
<fops:Notes>Field maintenance and inspection services</fops:Notes>
<fops:TransactionDateTime>2014-07-28T09:21:59</fops:TransactionDateTime>
<fops:TransactionIdentifier>51327</fops:TransactionIdentifier>
<fops:ActionSource role="DocumentActionPerformer">
<fops:FirstName>Carlos</fops:FirstName>
<fops:LastName>Jackson</fops:LastName>
<fops:EmailAddress>kristenturner@acosta.biz</fops:EmailAddress>
<fops:Location>
<fops:LocationCode siteCodeIndicator="AssignedByClient">AT-9284-QXWS</fops:LocationCode>
<fops:LocationName>Leader Block</fops:LocationName>
</fops:Location>
<fops:Department>
<fops:DepartmentName>Accounts Payable</fops:DepartmentName>
</fops:Department>
</fops:ActionSource>
</fops:Action>
<fops:PeriodDate>2014-04-16</fops:PeriodDate>
<fops:DiscountTotal>0</fops:DiscountTotal>
<fops:CurrentOwner>
<fops:Department>
<fops:DepartmentName>Accounts Payable</fops:DepartmentName>
</fops:Department>
</fops:CurrentOwner>
</fops:DocumentHeader>
<fops:DocumentLines>
<fops:Allocation>
<fops:AllocationRate>1</fops:AllocationRate>
<fops:Total>466</fops:Total>
</fops:Allocation>
<fops:LineEntry>
<fops:LineNumber>1</fops:LineNumber>
<fops:Quantity>1</fops:Quantity>
<fops:UnitPrice>466</fops:UnitPrice>
<fops:Notes>Wellsite services rendered per contract terms</fops:Notes>
<fops:PeriodDate>2014-04-16</fops:PeriodDate>
<fops:Discount>
<fops:Total>0</fops:Total>
<fops:AllocationRate>0</fops:AllocationRate>
</fops:Discount>
<fops:Category CategorizationScheme="ocpChargeType">
<fops:CategoryCode>Other</fops:CategoryCode>
</fops:Category>
<fops:Allocation>
<fops:AllocationRate>1</fops:AllocationRate>
<fops:Total>466</fops:Total>
</fops:Allocation>
<fops:ChargeClass>Non-Itemized</fops:ChargeClass>
</fops:LineEntry>
</fops:DocumentLines>
</fops:SummaryInvoice>
<fops:Attachments numOfAttachments="2">
<fops:Attachment type="pdfInvoice" id="0genPdf64899656">
<fops:LocationPath>/docp/supply-chain/v1/invoices/64899656/snapshot</fops:LocationPath>
<fops:ContentType>application/pdf</fops:ContentType>
</fops:Attachment>
</fops:Attachments>
</fops:StandardBillingDocument>
