<?xml version='1.0' encoding='UTF-8'?>
<fops:StandardBillingDocument xmlns:fops="http://www.fieldops-demo.io/xml/ns" type="APINVOICE"><fops:DetailedInvoice id="64471663">
<fops:DocumentHeader>
<fops:DocumentNumber>3654753724</fops:DocumentNumber>
<fops:Party PartyRole="Vendor">
<fops:Entity>
<fops:EntityCode EntityCodeType="VendorID">VEND508014</fops:EntityCode>
<fops:EntityName>Beasley Dennis and Ray</fops:EntityName>
</fops:Entity>
<fops:Location>
<fops:LocationCode LocationCodeType="AssignedByClient">IB-1714-BJWF</fops:LocationCode>
<fops:LocationName>Budget Lease</fops:LocationName>
<fops:Address AddressType="Mailing">
<fops:AddressLine>6442 Flowers Key</fops:AddressLine>
<fops:City>Ellistown</fops:City>
<fops:StateProvince>Texas</fops:StateProvince>
<fops:StateProvinceCode>TX</fops:StateProvinceCode>
<fops:Country>United States of America</fops:Country>
<fops:CountryCode>US</fops:CountryCode>
<fops:PostalZipCode>56394</fops:PostalZipCode>
<fops:PhoneNumber PhoneNumberType="Primary">5546367058</fops:PhoneNumber>
<fops:EmailAddress>lisa32@mitchell.com</fops:EmailAddress>
</fops:Address>
</fops:Location>
</fops:Party>
<fops:Party PartyRole="Client">
<fops:Entity>
<fops:EntityCode EntityCodeType="GlobalID">566248358</fops:EntityCode>
<fops:EntityName>Gonzales Peterson and Moore</fops:EntityName>
</fops:Entity>
<fops:Location>
<fops:LocationCode LocationCodeType="AssignedByClient">EM-3286-RSWG</fops:LocationCode>
<fops:LocationName>Out Block</fops:LocationName>
<fops:Address AddressType="Mailing">
<fops:AddressLine>689 Kelly Plaza Suite 688</fops:AddressLine>
<fops:City>Michaelfort</fops:City>
<fops:StateProvince>Oklahoma</fops:StateProvince>
<fops:StateProvinceCode>OK</fops:StateProvinceCode>
<fops:Country>United States of America</fops:Country>
<fops:CountryCode>US</fops:CountryCode>
<fops:PostalZipCode>15708</fops:PostalZipCode>
</fops:Address>
</fops:Location>
</fops:Party>
<fops:DocumentDate>2015-02-24</fops:DocumentDate>
<fops:DocumentType>Original Invoice</fops:DocumentType>
<fops:SubmissionMethod>Supplier_Regular_Direct</fops:SubmissionMethod>
<fops:Total>492</fops:Total>
<fops:VendorTotal>492</fops:VendorTotal>
<fops:LineCount>1</fops:LineCount>
<fops:Notes>Electrical installation and commissioning</fops:Notes>
<fops:CurrencyCode>USD</fops:CurrencyCode>
<fops:Action>
<fops:Contact Role="DocumentActionPerformer">
<fops:FirstName>Nicole</fops:FirstName>
<fops:LastName>Wilson</fops:LastName>
<fops:EmailAddress>ddouglas@nguyen.com</fops:EmailAddress>
<fops:Location>
<fops:LocationCode LocationCodeType="AssignedByClient">RS-1752-UFWT</fops:LocationCode>
<fops:LocationName>Score Lease</fops:LocationName>
</fops:Location>
<fops:Department>
<fops:DepartmentName>Accounts Payable</fops:DepartmentName>
</fops:Department>
</fops:Contact>
<fops:ActionType>Approve</fops:ActionType>
<fops:Status>Approved</fops:Status>
<fops:Notes>Pipeline integrity assessment services</fops:Notes>
<fops:TransactionDateTime>2014-07-02T13:00:19</fops:TransactionDateTime>
<fops:TransactionIdentifier>51327</fops:TransactionIdentifier>
<fops:ActionSource role="DocumentActionPerformer">
<fops:FirstName>Jason</fops:FirstName>
<fops:LastName>Velasquez</fops:LastName>
<fops:EmailAddress>bradherring@gomez-gibson.info</fops:EmailAddress>
<fops:Location>
<fops:LocationCode siteCodeIndicator="AssignedByClient">LS-9494-QMWF</fops:LocationCode>
<fops:LocationName>Project Basin</fops:LocationName>
</fops:Location>
<fops:Department>
<fops:DepartmentName>Accounts Payable</fops:DepartmentName>
</fops:Department>
</fops:ActionSource>
</fops:Action>
<fops:DiscountTotal>0</fops:DiscountTotal>
<fops:CurrentOwner>
<fops:Department>
<fops:DepartmentName>Accounts Payable</fops:DepartmentName>
</fops:Department>
</fops:CurrentOwner>
</fops:DocumentHeader>
<fops:DocumentLines>
<fops:LineEntry>
<fops:LineNumber>1</fops:LineNumber>
<fops:ServiceItem>
<fops:ServiceCode codeIndicator="AssignedByVendor">PRODUCT</fops:ServiceCode>
<fops:ProductDescription>Flowback Equipment</fops:ProductDescription>
</fops:ServiceItem>
<fops:Quantity>1</fops:Quantity>
<fops:UnitPrice>492</fops:UnitPrice>
<fops:Notes>Wellsite services rendered per contract terms</fops:Notes>
<fops:Discount>
<fops:Total>0</fops:Total>
<fops:AllocationRate>0</fops:AllocationRate>
</fops:Discount>
<fops:LineSubTotal>492</fops:LineSubTotal>
<fops:LinePretaxTotal>492</fops:LinePretaxTotal>
<fops:Total>492</fops:Total>
<fops:Category CategorizationScheme="ocpChargeType">
<fops:CategoryCode>Other</fops:CategoryCode>
</fops:Category>
<fops:Allocation>
<fops:AllocationRate>1</fops:AllocationRate>
<fops:Total>492</fops:Total>
</fops:Allocation>
<fops:ChargeClass>Itemized</fops:ChargeClass>
</fops:LineEntry>
</fops:DocumentLines>
</fops:DetailedInvoice>
<fops:Attachments numOfAttachments="2">
<fops:Attachment type="pdfInvoice" id="0genPdf64471663">
<fops:LocationPath>/docp/supply-chain/v1/invoices/64471663/snapshot</fops:LocationPath>
<fops:ContentType>application/pdf</fops:ContentType>
</fops:Attachment>
</fops:Attachments>
</fops:StandardBillingDocument>
