<?xml version='1.0' encoding='UTF-8'?>
<fops:StandardBillingDocument xmlns:fops="http://www.fieldops-demo.io/xml/ns" type="APINVOICE"><fops:DetailedInvoice id="65073455">
<fops:DocumentHeader>
<fops:DocumentNumber>4080871894</fops:DocumentNumber>
<fops:Party PartyRole="Vendor">
<fops:Entity>
<fops:EntityCode EntityCodeType="VendorID">VEND279134</fops:EntityCode>
<fops:EntityName>Johnson Mccullough and Zuniga</fops:EntityName>
</fops:Entity>
<fops:Location>
<fops:LocationCode LocationCodeType="AssignedByClient">SE-7799-DDWK</fops:LocationCode>
<fops:LocationName>Certainly Lease</fops:LocationName>
<fops:Address AddressType="Mailing">
<fops:AddressLine>657 Kelly Pine</fops:AddressLine>
<fops:City>Jamesshire</fops:City>
<fops:StateProvince>Texas</fops:StateProvince>
<fops:StateProvinceCode>TX</fops:StateProvinceCode>
<fops:Country>United States of America</fops:Country>
<fops:CountryCode>US</fops:CountryCode>
<fops:PostalZipCode>42500</fops:PostalZipCode>
<fops:PhoneNumber PhoneNumberType="Primary">3980602508</fops:PhoneNumber>
<fops:EmailAddress>lindseykirby@williams.com</fops:EmailAddress>
</fops:Address>
</fops:Location>
</fops:Party>
<fops:Party PartyRole="Client">
<fops:Entity>
<fops:EntityCode EntityCodeType="GlobalID">709781867</fops:EntityCode>
<fops:EntityName>Vargas PLC</fops:EntityName>
</fops:Entity>
<fops:Location>
<fops:LocationCode LocationCodeType="AssignedByClient">OZ-3717-HTWN</fops:LocationCode>
<fops:LocationName>Building Block</fops:LocationName>
<fops:Address AddressType="Mailing">
<fops:AddressLine>00005 Landry Walks</fops:AddressLine>
<fops:City>Myersside</fops:City>
<fops:StateProvince>Oklahoma</fops:StateProvince>
<fops:StateProvinceCode>OK</fops:StateProvinceCode>
<fops:Country>United States of America</fops:Country>
<fops:CountryCode>US</fops:CountryCode>
<fops:PostalZipCode>67173</fops:PostalZipCode>
</fops:Address>
</fops:Location>
</fops:Party>
<fops:DocumentDate>2015-03-30</fops:DocumentDate>
<fops:DocumentType>Original Invoice</fops:DocumentType>
<fops:SubmissionMethod>Supplier_Regular_Direct</fops:SubmissionMethod>
<fops:Total>674.7</fops:Total>
<fops:VendorTotal>674.7</fops:VendorTotal>
<fops:LineCount>1</fops:LineCount>
<fops:Notes>Field maintenance and inspection services</fops:Notes>
<fops:CurrencyCode>USD</fops:CurrencyCode>
<fops:Action>
<fops:Contact Role="DocumentActionPerformer">
<fops:FirstName>Troy</fops:FirstName>
<fops:LastName>Thomas</fops:LastName>
<fops:EmailAddress>dana23@lamb.com</fops:EmailAddress>
<fops:Location>
<fops:LocationCode LocationCodeType="AssignedByClient">UT-0442-ICWC</fops:LocationCode>
<fops:LocationName>All Pad</fops:LocationName>
</fops:Location>
<fops:Department>
<fops:DepartmentName>Accounts Payable</fops:DepartmentName>
</fops:Department>
</fops:Contact>
<fops:ActionType>Approve</fops:ActionType>
<fops:Status>Approved</fops:Status>
<fops:Notes>Pipeline integrity assessment services</fops:Notes>
<fops:TransactionDateTime>2014-07-24T10:20:54</fops:TransactionDateTime>
<fops:TransactionIdentifier>51327</fops:TransactionIdentifier>
<fops:ActionSource role="DocumentActionPerformer">
<fops:FirstName>David</fops:FirstName>
<fops:LastName>Clark</fops:LastName>
<fops:EmailAddress>volson@reed.com</fops:EmailAddress>
<fops:Location>
<fops:LocationCode siteCodeIndicator="AssignedByClient">DV-9171-LJWZ</fops:LocationCode>
<fops:LocationName>Right Well</fops:LocationName>
</fops:Location>
<fops:Department>
<fops:DepartmentName>Accounts Payable</fops:DepartmentName>
</fops:Department>
</fops:ActionSource>
</fops:Action>
<fops:DiscountTotal>0</fops:DiscountTotal>
<fops:CurrentOwner>
<fops:Department>
<fops:DepartmentName>Accounts Payable</fops:DepartmentName>
</fops:Department>
</fops:CurrentOwner>
</fops:DocumentHeader>
<fops:DocumentLines>
<fops:LineEntry>
<fops:LineNumber>1</fops:LineNumber>
<fops:ServiceItem>
<fops:ServiceCode codeIndicator="AssignedByVendor">PRODUCT</fops:ServiceCode>
<fops:ProductDescription>Rod Pump</fops:ProductDescription>
</fops:ServiceItem>
<fops:Quantity>1</fops:Quantity>
<fops:UnitPrice>674.7</fops:UnitPrice>
<fops:Notes>Environmental monitoring and compliance</fops:Notes>
<fops:Discount>
<fops:Total>0</fops:Total>
<fops:AllocationRate>0</fops:AllocationRate>
</fops:Discount>
<fops:LineSubTotal>674.7</fops:LineSubTotal>
<fops:LinePretaxTotal>674.7</fops:LinePretaxTotal>
<fops:Total>674.7</fops:Total>
<fops:Category CategorizationScheme="ocpChargeType">
<fops:CategoryCode>Other</fops:CategoryCode>
</fops:Category>
<fops:Allocation>
<fops:AllocationRate>1</fops:AllocationRate>
<fops:Total>674.7</fops:Total>
</fops:Allocation>
<fops:ChargeClass>Itemized</fops:ChargeClass>
</fops:LineEntry>
</fops:DocumentLines>
</fops:DetailedInvoice>
<fops:Attachments numOfAttachments="2">
<fops:Attachment type="pdfInvoice" id="0genPdf65073455">
<fops:LocationPath>/docp/supply-chain/v1/invoices/65073455/snapshot</fops:LocationPath>
<fops:ContentType>application/pdf</fops:ContentType>
</fops:Attachment>
</fops:Attachments>
</fops:StandardBillingDocument>
